{
  "id": "rss-20260621-008",
  "title": "MolmoMotion: Language-guided 3D motion forecasting",
  "source": "rss:Hugging Face Blog",
  "source_url": "https://huggingface.co/blog/allenai/molmomotion",
  "author": "Hugging Face Blog",
  "published_at": "2026-06-21T11:15:04.593010+00:00",
  "collected_at": "2026-06-21T11:15:04.593010+00:00",
  "summary": "MolmoMotion 是一种语言引导的3D运动预测技术，通过自然语言指令来生成和预测三维空间中的运动轨迹。该技术结合了语言理解和3D运动建模，为机器人导航、自动驾驶等应用提供了更直观的交互方式。",
  "score": 7,
  "tags": [
    "vision",
    "reasoning"
  ],
  "audience": "intermediate",
  "status": "review",
  "updated_at": "2026-06-21T11:16:20.592720+00:00"
}