{
  "id": "rss-20260719-001",
  "title": "AI Mania Is Eviscerating Global Decision-Making",
  "source": "rss:Hacker News (Best)",
  "source_url": "https://ludic.mataroa.blog/blog/ai-mania-is-eviscerating-global-decision-making/#fnref:3",
  "author": "Hacker News (Best)",
  "published_at": "2026-07-19T09:51:38.651727+00:00",
  "collected_at": "2026-07-19T09:51:38.651727+00:00",
  "summary": "文章批评当前AI热潮正在破坏全球决策质量，指出过度依赖AI可能导致认知能力下降和判断失误。核心价值在于警示AI技术的潜在风险，呼吁理性看待AI在决策中的作用。",
  "score": 7,
  "tags": [
    "reasoning",
    "evaluation"
  ],
  "audience": "intermediate",
  "status": "review",
  "updated_at": "2026-07-19T09:52:53.802278+00:00"
}